AzureDataLakeStorageLibrary/AzureDataLakeStorageLibrary.py
AzureDataLakeStorageLibrary/__init__.py
robotframework_adls_library-0.0.1.dist-info/METADATA
robotframework_adls_library-0.0.1.dist-info/WHEEL
robotframework_adls_library-0.0.1.dist-info/RECORD
